boxup_weatherradar
