Metadata-Version: 1.1
Name: boxup-weatherradar
Version: 0.0.2
Summary: datasource for boxup input
Home-page: https://github.com/xamgreen/boxup_weatherradar
Author: Maximilian, Noppel
Author-email: noppelmax@googlemail.com
License: GPLv2, see LICENSE.txt
Download-URL: https://github.com/xamgreen/boxup_weatherradar/tarball/0.0.2
Keywords: weatherradar,openweathermap,raspberrypi,gpio,adafruit,bicolormatrix
Platform: UNKNOWN
